HRC/__init__.py
HRC/main.py
HRC-0.3.1.dist-info/METADATA
HRC-0.3.1.dist-info/WHEEL
HRC-0.3.1.dist-info/top_level.txt
HRC-0.3.1.dist-info/RECORD
