Metadata-Version: 2.1
Name: HRC
Version: 0.3.1
